adafruit_tmp117.py
adafruit_circuitpython_tmp117-1.1.18.dist-info/licenses/LICENSE
adafruit_circuitpython_tmp117-1.1.18.dist-info/METADATA
adafruit_circuitpython_tmp117-1.1.18.dist-info/WHEEL
adafruit_circuitpython_tmp117-1.1.18.dist-info/top_level.txt
adafruit_circuitpython_tmp117-1.1.18.dist-info/RECORD
